abstractcode/__init__.py
abstractcode/cli.py
abstractcode/flow_cli.py
abstractcode/fullscreen_ui.py
abstractcode/input_handler.py
abstractcode/py.typed
abstractcode/react_shell.py
abstractcode/recall.py
abstractcode/remember.py
abstractcode/terminal_markdown.py
abstractcode/workflow_agent.py
abstractcode-0.3.0.dist-info/licenses/LICENSE
abstractcode-0.3.0.dist-info/METADATA
abstractcode-0.3.0.dist-info/WHEEL
abstractcode-0.3.0.dist-info/entry_points.txt
abstractcode-0.3.0.dist-info/top_level.txt
abstractcode-0.3.0.dist-info/RECORD
