Metadata-Version: 2.4
Name: abstractcode
Version: 0.3.0
Summary: A clean terminal CLI for multi-agent agentic coding
Author-email: Laurent-Philippe Albou <contact@abstractcore.ai>
Maintainer-email: Laurent-Philippe Albou <contact@abstractcore.ai>
License: MIT
Project-URL: Homepage, https://abstractcore.ai
Project-URL: Documentation, https://abstractcore.ai
Project-URL: Repository, https://github.com/lpalbou/abstractcode
Project-URL: Bug Tracker, https://github.com/lpalbou/abstractcode/issues
Keywords: ai,llm,cli,coding,agent,multi-agent,agentic,terminal,abstractcore,abstractruntime,abstractagent
Classifier: Development Status :: 2 - Pre-Alpha
Classifier: Intended Audience :: Developers
Classifier: License :: OSI Approved :: MIT License
Classifier: Operating System :: OS Independent
Classifier: Programming Language :: Python :: 3
Classifier: Programming Language :: Python :: 3.10
Classifier: Programming Language :: Python :: 3.11
Classifier: Programming Language :: Python :: 3.12
Classifier: Topic :: Software Development :: Libraries :: Python Modules
Classifier: Topic :: Scientific/Engineering :: Artificial Intelligence
Requires-Python: >=3.10
License-File: LICENSE
Requires-Dist: abstractagent>=0.2.0
Requires-Dist: abstractruntime>=0.2.0
Requires-Dist: abstractcore[tools]>=2.6.8
Requires-Dist: ddgs<10.0.0,>=9.10.0
Requires-Dist: prompt_toolkit>=3.0.0
Provides-Extra: dev
Requires-Dist: pytest>=7.0.0; extra == "dev"
Requires-Dist: pytest-cov>=4.0.0; extra == "dev"
Requires-Dist: black>=23.0.0; extra == "dev"
Requires-Dist: ruff>=0.1.0; extra == "dev"
Provides-Extra: flow
Requires-Dist: abstractflow>=0.1.0; extra == "flow"
Dynamic: license-file
